{
  "work": {
    "id": "d9850998-268a-3114-a208-a16a9f79766f",
    "title": "Choral, BWV 298 "Dies sind die heil'gen zehn Gebot'"",
    "language": "deu",
    "alias-list": [
      {
        "sort-name": "Choralvorspiel, BWV 635 / Choralsatz, BWV 298 "Dies sind die heilgen zehn Gebot"",
        "alias": "Choralvorspiel, BWV 635 / Choralsatz, BWV 298 "Dies sind die heilgen zehn Gebot""
      }
    ],
    "alias-count": 1,
    "artist-relation-list": [
      {
        "type": "composer",
        "type-id": "d59d99ea-23d4-4a80-b066-edca32ee158f",
        "target": "24f1766e-9635-4d58-a4d4-9413f9f98a4c",
        "direction": "backward",
        "artist": {
          "id": "24f1766e-9635-4d58-a4d4-9413f9f98a4c",
          "type": "Person",
          "name": "Johann Sebastian Bach",
          "sort-name": "Bach, Johann Sebastian",
          "disambiguation": "German Baroque period composer & musician"
        }
      },
      {
        "type": "lyricist",
        "type-id": "3e48faba-ec01-47fd-8e89-30e81161661c",
        "target": "5a90e31d-52f3-4966-8ce0-7c3818fccca3",
        "direction": "backward",
        "artist": {
          "id": "5a90e31d-52f3-4966-8ce0-7c3818fccca3",
          "type": "Person",
          "name": "Martin Luther",
          "sort-name": "Luther, Martin",
          "disambiguation": "German theologian of the Reformation"
        }
      }
    ],
    "recording-relation-list": [
      {
        "type": "performance",
        "type-id": "a3005666-a872-32c3-ad06-98af558e99b0",
        "target": "def8ad8b-e515-475b-ad9a-2df83126c368",
        "direction": "backward",
        "begin": "1998-09",
        "end": "1998-09",
        "ended": "true",
        "recording": {
          "id": "def8ad8b-e515-475b-ad9a-2df83126c368",
          "title": "Choralvorspiel, BWV 635 / Choralsatz, BWV 298 „Dies sind die heilgen zehn Gebot“",
          "length": "162000"
        }
      },
      {
        "type": "performance",
        "type-id": "a3005666-a872-32c3-ad06-98af558e99b0",
        "target": "9fdf76a5-df84-4c0e-83ef-c74653db5868",
        "direction": "backward",
        "begin": "1999-06",
        "end": "1999-06",
        "ended": "true",
        "recording": {
          "id": "9fdf76a5-df84-4c0e-83ef-c74653db5868",
          "title": "Dies sind die heil'gen zehn Gebot', BWV 298",
          "length": "41000"
        }
      },
      {
        "type": "performance",
        "type-id": "a3005666-a872-32c3-ad06-98af558e99b0",
        "target": "4230c29b-150c-41e4-aef2-9cc2997a52f4",
        "direction": "backward",
        "begin": "1999",
        "end": "1999",
        "ended": "true",
        "recording": {
          "id": "4230c29b-150c-41e4-aef2-9cc2997a52f4",
          "title": "BWV 298: Dies sind die heil'gen zehn Gebot'",
          "length": "51333"
        }
      },
      {
        "type": "performance",
        "type-id": "a3005666-a872-32c3-ad06-98af558e99b0",
        "target": "65693fb3-2ece-4f2c-b51c-0ae220f92ab5",
        "direction": "backward",
        "begin": "2007",
        "end": "2007",
        "ended": "true",
        "recording": {
          "id": "65693fb3-2ece-4f2c-b51c-0ae220f92ab5",
          "title": "Choral, BWV 298 "Dies sind die heil'gen zehn Gebot'"",
          "length": "66466"
        }
      },
      {
        "type": "performance",
        "type-id": "a3005666-a872-32c3-ad06-98af558e99b0",
        "target": "a67ed555-d1fa-41c2-9e10-9dada87498cd",
        "direction": "backward",
        "begin": "2017-07",
        "end": "2017-07",
        "ended": "true",
        "recording": {
          "id": "a67ed555-d1fa-41c2-9e10-9dada87498cd",
          "title": "Dies sind die heil'gen zehn Gebot', BWV 298",
          "length": "46746"
        }
      },
      {
        "type": "performance",
        "type-id": "a3005666-a872-32c3-ad06-98af558e99b0",
        "target": "fd7c8327-b921-4d7b-aa9f-488731767b8a",
        "direction": "backward",
        "recording": {
          "id": "fd7c8327-b921-4d7b-aa9f-488731767b8a",
          "title": "Choral: Dies sind die heil'gen Zehn Gebot, BWV 298",
          "length": "56533"
        }
      }
    ],
    "series-relation-list": [
      {
        "type": "part of",
        "type-id": "b0d44366-cdf0-3acb-bee6-0f65a77a6ef0",
        "target": "d977f7fd-96c9-4e3e-83b5-eb484a9e6582",
        "ordering-key": "317",
        "direction": "backward",
        "attribute-list": [
          "number"
        ],
        "series": {
          "id": "d977f7fd-96c9-4e3e-83b5-eb484a9e6582",
          "type": "Catalogue",
          "name": "Bach-Werke-Verzeichnis"
        },
        "attributes": [
          {
            "type-id": "a59c5830-5ec7-38fe-9a21-c7ea54f6650a",
            "value": "BWV 298",
            "attribute": "number"
          }
        ]
      },
      {
        "type": "part of",
        "type-id": "b0d44366-cdf0-3acb-bee6-0f65a77a6ef0",
        "target": "1b6aec18-db22-4f91-98fb-2a5770183374",
        "ordering-key": "66",
        "direction": "backward",
        "attribute-list": [
          "number"
        ],
        "series": {
          "id": "1b6aec18-db22-4f91-98fb-2a5770183374",
          "type": "Catalogue",
          "name": "Breitkopf 389 Choralgesänge"
        },
        "attributes": [
          {
            "type-id": "a59c5830-5ec7-38fe-9a21-c7ea54f6650a",
            "value": "66",
            "attribute": "number"
          }
        ]
      }
    ]
  }
}